prom2icinga2/__init__.py
prom2icinga2/_scm_version.py
prom2icinga2/config.py
prom2icinga2/icinga2.py
prom2icinga2/prometheus.py
prom2icinga2/server.py
prom2icinga2-0.4.0.dist-info/LICENSE.md
prom2icinga2-0.4.0.dist-info/METADATA
prom2icinga2-0.4.0.dist-info/WHEEL
prom2icinga2-0.4.0.dist-info/entry_points.txt
prom2icinga2-0.4.0.dist-info/top_level.txt
prom2icinga2-0.4.0.dist-info/RECORD
