Metadata-Version: 2.2
Name: prom2icinga2
Version: 0.4.0
Author: DinoTools
License: ### GNU GENERAL PUBLIC LICENSE
Project-URL: Homepage, https://github.com/DinoTools/prom2icinga2
Keywords: Prometheus,Icinga2,Monitoring
Classifier: Development Status :: 3 - Alpha
Classifier: License :: OSI Approved :: GNU General Public License v3 or later (GPLv3+)
Classifier: Programming Language :: Python
Classifier: Programming Language :: Python :: 3
Requires-Python: >=3.8
License-File: LICENSE.md
Requires-Dist: fastapi
Requires-Dist: httpx
Requires-Dist: jinja2
Requires-Dist: pydantic>2.0.0
Requires-Dist: pydantic-settings>2.0.0
Requires-Dist: pyyaml
Requires-Dist: uvicorn
